down/__init__.py
down/encryption.py
down/main.py
ajab_gg-0.0.6.dist-info/METADATA
ajab_gg-0.0.6.dist-info/WHEEL
ajab_gg-0.0.6.dist-info/top_level.txt
ajab_gg-0.0.6.dist-info/RECORD
