Metadata-Version: 2.1
Name: ajab-gg
Version: 0.0.6
Summary: This is a powerful library for building self robots in Rubika
Home-page: https://web.rubika.ir
Author: OKB
Author-email: aliahmad@gmail.com
Keywords: rubika
Classifier: Programming Language :: Python :: 3.6
Classifier: Programming Language :: Python :: 3.7
Classifier: Programming Language :: Python :: 3.8
Classifier: Programming Language :: Python :: 3.9
Classifier: Programming Language :: Python :: 3.10
Classifier: Programming Language :: Python :: 3.11
Classifier: License :: OSI Approved :: MIT License
Requires-Python: ~=3.7
Requires-Dist: requests
Requires-Dist: ujson
Requires-Dist: urllib3
Requires-Dist: pycryptodome
Requires-Dist: rubiran
